victorpy
