Metadata-Version: 1.1
Name: victorpy
Version: 0.1.32
Summary: A simple yet powerful static site generator with Python sugar
Home-page: https://github.com/pascallando/victorpy
Author: Pascal LANDO
Author-email: pascal.lando@u-picardie.fr
License: UNKNOWN
Keywords: static site,python
Platform: UNKNOWN
Classifier: Environment :: Console
Classifier: Operating System :: OS Independent
Classifier: Programming Language :: Python :: 3.6
Classifier: Topic :: Internet :: WWW/HTTP
Classifier: Topic :: Software Development :: Libraries :: Python Modules
